LICENSE
MANIFEST.in
README.md
setup.py
mkdocs_encriptmail_plugin.egg-info/PKG-INFO
mkdocs_encriptmail_plugin.egg-info/SOURCES.txt
mkdocs_encriptmail_plugin.egg-info/dependency_links.txt
mkdocs_encriptmail_plugin.egg-info/entry_points.txt
mkdocs_encriptmail_plugin.egg-info/requires.txt
mkdocs_encriptmail_plugin.egg-info/top_level.txt
src/__init__.py
src/plugin.py
src/__pycache__/__init__.cpython-38.pyc
src/__pycache__/plugin.cpython-38.pyc
src/js/encriptmail.js