Metadata-Version: 2.1
Name: mkdocs-encriptmail-plugin
Version: 0.9.5
Summary: A MkDocs plugin that converts markdown encoded email-links into spambot save <a href> elements.
Home-page: https://github.com/Rolfff/mkdocs-encriptmail-plugin
Author: Rolfff
License: MIT
Keywords: mkdocs python markdown
Platform: UNKNOWN
Requires-Python: >=3.5
